LICENSE
MANIFEST.in
README.md
requirements.txt
setup.cfg
setup.py
versioneer.py
botcity/base/__init__.py
botcity/base/_version.py
botcity/base/bot.py
botcity/base/state.py
botcity/base/utils.py
botcity/base/tests/__init__.py
botcity/base/tests/test_import.py
botcity_framework_base.egg-info/PKG-INFO
botcity_framework_base.egg-info/SOURCES.txt
botcity_framework_base.egg-info/dependency_links.txt
botcity_framework_base.egg-info/top_level.txt