Metadata-Version: 2.1
Name: botcity-framework-base
Version: 0.1.0
Summary: UNKNOWN
Home-page: https://www.github.com/botcity-dev/botcity-framework-base-python
License: UNKNOWN
Platform: UNKNOWN
Requires-Python: >=3.7
License-File: LICENSE
